odoo/addons/project_task_description_portal/README.rst
odoo/addons/project_task_description_portal/__init__.py
odoo/addons/project_task_description_portal/__manifest__.py
odoo/addons/project_task_description_portal/controllers/__init__.py
odoo/addons/project_task_description_portal/controllers/portal.py
odoo/addons/project_task_description_portal/i18n/it.po
odoo/addons/project_task_description_portal/i18n/project_task_description_portal.pot
odoo/addons/project_task_description_portal/i18n/pt.po
odoo/addons/project_task_description_portal/models/__init__.py
odoo/addons/project_task_description_portal/models/project_task.py
odoo/addons/project_task_description_portal/readme/CONFIGURE.md
odoo/addons/project_task_description_portal/readme/CONTEXT.md
odoo/addons/project_task_description_portal/readme/CONTRIBUTORS.md
odoo/addons/project_task_description_portal/readme/DESCRIPTION.md
odoo/addons/project_task_description_portal/readme/ROADMAP.md
odoo/addons/project_task_description_portal/readme/USAGE.md
odoo/addons/project_task_description_portal/static/description/icon.png
odoo/addons/project_task_description_portal/static/description/index.html
odoo/addons/project_task_description_portal/static/description/img/portal_description.png
odoo/addons/project_task_description_portal/static/description/img/portal_view.png
odoo/addons/project_task_description_portal/static/description/img/use_portal_description.png
odoo/addons/project_task_description_portal/views/project_portal_templates.xml
odoo/addons/project_task_description_portal/views/project_task_views.xml
odoo_addon_project_task_description_portal-18.0.1.0.0.2.dist-info/METADATA
odoo_addon_project_task_description_portal-18.0.1.0.0.2.dist-info/WHEEL
odoo_addon_project_task_description_portal-18.0.1.0.0.2.dist-info/top_level.txt
odoo_addon_project_task_description_portal-18.0.1.0.0.2.dist-info/RECORD
